gpio4/__init__.py
gpio4/arduino.py
gpio4/constants.py
gpio4-0.1.6.dist-info/LICENSE
gpio4-0.1.6.dist-info/METADATA
gpio4-0.1.6.dist-info/WHEEL
gpio4-0.1.6.dist-info/top_level.txt
gpio4-0.1.6.dist-info/RECORD
