Metadata-Version: 2.1
Name: gpio4
Version: 0.1.6
Summary: Improved gpio module based on Sysfs, features same as RPi.GPIO and gpio3
Home-page: https://github.com/hankso/gpio4
Author: hankso
Author-email: hankso1106@gmail.com
License: UNKNOWN
Platform: UNKNOWN
Classifier: Development Status :: 3 - Alpha
Classifier: License :: OSI Approved :: MIT License
Classifier: Programming Language :: Python
Classifier: Topic :: System :: Hardware :: Hardware Drivers
